djcode/__init__.py
djcode/djcode.py
djsbmp/__init__.py
djsbmp/djsbmp.py
djsbmpc/__init__.py
djsbmpc/djsbmp.py
sbmp/__init__.py
sbmp/djsbmp.py
sbmp/sbmp.py
djcode-2.5.1.dist-info/LICENSE
djcode-2.5.1.dist-info/METADATA
djcode-2.5.1.dist-info/WHEEL
djcode-2.5.1.dist-info/top_level.txt
djcode-2.5.1.dist-info/RECORD
